{
    "path": "https://api.oldmartijntje.nl/api/oldmartijntje.nl/assets/images/ads",
    "folders": [
        {
            "name": "source",
            "childrenAmount": 4,
            "lastModified": 1716379916.0769303,
            "type": "folder"
        }
    ],
    "files": [
        {
            "name": "battlePainters.gif",
            "size": 10198,
            "lastModified": 1716379916.0574036,
            "type": "gif"
        },
        {
            "name": "brainTraining.gif",
            "size": 4914,
            "lastModified": 1716379916.0589097,
            "type": "gif"
        },
        {
            "name": "Button1.gif",
            "size": 3725,
            "lastModified": 1716379916.0574036,
            "type": "gif"
        },
        {
            "name": "carcassonne.gif",
            "size": 1049724,
            "lastModified": 1716379916.0654001,
            "type": "gif"
        },
        {
            "name": "index.html",
            "size": 17956,
            "lastModified": 1716381348.5839624,
            "type": "html"
        },
        {
            "name": "index.json",
            "size": 2478,
            "lastModified": 1716381348.5898001,
            "type": "json"
        },
        {
            "name": "longus.gif",
            "size": 8035,
            "lastModified": 1716379916.0663977,
            "type": "gif"
        },
        {
            "name": "marioScared.png",
            "size": 49268,
            "lastModified": 1716379916.0663977,
            "type": "png"
        },
        {
            "name": "nicelyCSSed.gif",
            "size": 11738,
            "lastModified": 1716379916.0663977,
            "type": "gif"
        },
        {
            "name": "partnerzInTiem.gif",
            "size": 83287,
            "lastModified": 1716379916.067396,
            "type": "gif"
        },
        {
            "name": "robuzx.png",
            "size": 4200,
            "lastModified": 1716379916.067396,
            "type": "png"
        },
        {
            "name": "scratch.gif",
            "size": 503778,
            "lastModified": 1716379916.0719438,
            "type": "gif"
        },
        {
            "name": "single.gif",
            "size": 15156,
            "lastModified": 1716379916.0729413,
            "type": "gif"
        }
    ],
    "parent": "../index.json"
}