{
    "path": "https://oldmartijntje.github.io/json-api/api/standaloneWebsites/404pages",
    "folders": [
        {
            "name": "basic_nsmbds404",
            "childrenAmount": 3,
            "lastModified": 1717233400.33694,
            "type": "folder"
        }
    ],
    "files": [
        {
            "name": "index.html",
            "size": 11592,
            "lastModified": 1729115947.613816,
            "type": "html"
        },
        {
            "name": "index.json",
            "size": 670,
            "lastModified": 1729115947.6168277,
            "type": "json"
        }
    ],
    "parent": "../index.json"
}